README
setup.py
amptrac/__init__.py
amptrac/client.py
amptrac/commands.py
amptrac.egg-info/PKG-INFO
amptrac.egg-info/SOURCES.txt
amptrac.egg-info/dependency_links.txt
amptrac.egg-info/not-zip-safe
amptrac.egg-info/requires.txt
amptrac.egg-info/top_level.txt
amptrac/test/__init__.py