Metadata-Version: 1.0
Name: amptrac
Version: 0.1
Summary: Client for twisted's amp interface to trac
Home-page: https://github.com/tomprince/amptrac
Author: Tom Prince
Author-email: tom.prince@ualberta.net
License: MIT
Platform: UNKNOWN
